pacifica_notifications-0.5.2-py3.8-nspkg.pth
pacifica/notifications/__init__.py
pacifica/notifications/__main__.py
pacifica/notifications/config.py
pacifica/notifications/globals.py
pacifica/notifications/jsonpath.py
pacifica/notifications/orm.py
pacifica/notifications/rest.py
pacifica/notifications/tasks.py
pacifica/notifications/wsgi.py
pacifica_notifications-0.5.2.dist-info/LICENSE
pacifica_notifications-0.5.2.dist-info/METADATA
pacifica_notifications-0.5.2.dist-info/WHEEL
pacifica_notifications-0.5.2.dist-info/entry_points.txt
pacifica_notifications-0.5.2.dist-info/namespace_packages.txt
pacifica_notifications-0.5.2.dist-info/top_level.txt
pacifica_notifications-0.5.2.dist-info/RECORD
