Metadata-Version: 2.1
Name: pacifica-notifications
Version: 0.5.2
Summary: Pacifica Notifications Service
Home-page: https://github.com/pacifica/pacifica-notifications/
Author: David Brown
Author-email: dmlb2000@gmail.com
License: UNKNOWN
Platform: UNKNOWN
Requires-Dist: celery
Requires-Dist: cherrypy
Requires-Dist: jsonpath2
Requires-Dist: jsonschema
Requires-Dist: pacifica-namespace
Requires-Dist: peewee
Requires-Dist: requests
